pyfeld/__init__.py
pyfeld/__init__.pyc
pyfeld/browseRF.py
pyfeld/browseRF.pyc
pyfeld/dataPacker.py
pyfeld/dataPacker.pyc
pyfeld/didlInfo.py
pyfeld/didlInfo.pyc
pyfeld/dirBrowse.py
pyfeld/dirBrowse.pyc
pyfeld/dirBrowseExtended.py
pyfeld/dirBrowseExtended.pyc
pyfeld/discoverByHttp.py
pyfeld/discoverByHttp.pyc
pyfeld/errorPrint.py
pyfeld/errorPrint.pyc
pyfeld/getRaumfeld.py
pyfeld/getRaumfeld.pyc
pyfeld/raumfeldZone.py
pyfeld/raumfeldZone.pyc
pyfeld/rfcmd.py
pyfeld/rfcmd.pyc
pyfeld/room.py
pyfeld/room.pyc
pyfeld/run-test.py
pyfeld/run-test.pyc
pyfeld/settings.py
pyfeld/settings.pyc
pyfeld/stateVariables.py
pyfeld/stateVariables.pyc
pyfeld/tkui.py
pyfeld/tkui.pyc
pyfeld/upnpCommand.py
pyfeld/upnpCommand.pyc
pyfeld/upnpService.py
pyfeld/upnpService.pyc
pyfeld/upnpsoap.py
pyfeld/upnpsoap.pyc
pyfeld/xmlHelper.py
pyfeld/xmlHelper.pyc
pyfeld/zonesHandler.py
pyfeld/zonesHandler.pyc
pyfeld-0.2.1a0.dist-info/DESCRIPTION.rst
pyfeld-0.2.1a0.dist-info/METADATA
pyfeld-0.2.1a0.dist-info/RECORD
pyfeld-0.2.1a0.dist-info/WHEEL
pyfeld-0.2.1a0.dist-info/entry_points.txt
pyfeld-0.2.1a0.dist-info/metadata.json
pyfeld-0.2.1a0.dist-info/top_level.txt
